pyhmc/__init__.py
pyhmc/_hmc.cp310-win_amd64.pyd
pyhmc/_utils.cp310-win_amd64.pyd
pyhmc/_version.py
pyhmc/autocorr1.py
pyhmc/autocorr2.py
pyhmc/autocorr3.py
pyhmc/autocorr4.py
pyhmc/autocorr5.py
pyhmc/autocorr6.py
pyhmc/hmc.py
pyhmc/tests/__init__.py
pyhmc/tests/test_autocorr1.py
pyhmc/tests/test_autocorr2.py
pyhmc/tests/test_autocorr3.py
pyhmc/tests/test_autocorr4.py
pyhmc/tests/test_autocorr5.py
pyhmc/tests/test_autocorr6.py
pyhmc/tests/test_hmc.py
pyhmc_duplicate-1.0.0.dist-info/LICENSE
pyhmc_duplicate-1.0.0.dist-info/METADATA
pyhmc_duplicate-1.0.0.dist-info/WHEEL
pyhmc_duplicate-1.0.0.dist-info/top_level.txt
pyhmc_duplicate-1.0.0.dist-info/RECORD
