Metadata-Version: 2.1
Name: pyhmc-duplicate
Version: 1.0.0
Summary: This is a temperary duplicate version of pyhmc for msmbuilder2022 installation.
Home-page: https://github.com/rmcgibbo/pyhmc
Author: Robert T. McGibbon
Author-email: rmcgibbo@gmail.com
License: BSD
License-File: LICENSE
Requires-Dist: numpy
